LICENSE.txt
README.md
setup.cfg
setup.py
berkoidf/__init__.py
berkoidf.egg-info/PKG-INFO
berkoidf.egg-info/SOURCES.txt
berkoidf.egg-info/dependency_links.txt
berkoidf.egg-info/requires.txt
berkoidf.egg-info/top_level.txt
berkoidf/feature_extraction/__init__.py
berkoidf/feature_extraction/vectorizer.py
berkoidf/tests/__init__.py
berkoidf/tests/vectorizer_test.py