Metadata-Version: 2.1
Name: berkoidf
Version: 0.2
Home-page: https://github.com/berkedilekoglu/tfidfvectorizerinheritencecase
Download-URL: https://github.com/berkedilekoglu/tfidfvectorizerinheritencecase/archive/refs/tags/vectorizer.tar.gz
Author: Berke Dilekoglu
License: MIT
Keywords: machine-learning tf-idf
License-File: LICENSE.txt
